veraverto/__init__.py
veraverto-0.0.1.dist-info/LICENSE
veraverto-0.0.1.dist-info/METADATA
veraverto-0.0.1.dist-info/WHEEL
veraverto-0.0.1.dist-info/top_level.txt
veraverto-0.0.1.dist-info/RECORD
