Metadata-Version: 2.1
Name: veraverto
Version: 0.0.1
Summary: BOT and CLI framework for handling multiple services in python
Home-page: https://github.com/Beluuuuuuga/veraverto
Author: beluga
Author-email: inoue.koki15@gmail.com
License: UNKNOWN
Platform: UNKNOWN
Classifier: Programming Language :: Python :: 3.7
Classifier: License :: OSI Approved :: MIT License
Classifier: Operating System :: OS Independent
